bakepy/__about__.py
bakepy/__init__.py
bakepy/html.py
bakepy/ipython.py
bakepy/recipes.py
bakepy/rendering.py
bakepy/report.py
bakepy/utils.py
bakepy-0.0.11.dist-info/METADATA
bakepy-0.0.11.dist-info/WHEEL
bakepy-0.0.11.dist-info/licenses/LICENSE.txt
bakepy-0.0.11.dist-info/RECORD
