Metadata-Version: 2.1
Name: bakepy
Version: 0.0.11
Summary: BakePy Reporting Library
Project-URL: Homepage, https://github.com/mgczacki/bakepy
Author-email: Mario Garrido <mg@czacki.com>
License-File: LICENSE.txt
Requires-Python: >=3.7
Requires-Dist: beautifulsoup4==4.11.1
Requires-Dist: markdown-katex==202112.1034
Requires-Dist: markdown==3.3.6
Requires-Dist: requests==2.26.0
Provides-Extra: complete
Requires-Dist: matplotlib; extra == 'complete'
Requires-Dist: pandas; extra == 'complete'
